pailettes/__init__.py
pailettes/main.py
pailettes-0.1.4.dist-info/entry_points.txt
pailettes-0.1.4.dist-info/WHEEL
pailettes-0.1.4.dist-info/LICENSE
pailettes-0.1.4.dist-info/METADATA
pailettes-0.1.4.dist-info/RECORD
