Metadata-Version: 2.1
Name: pailettes
Version: 0.1.4
Summary: Generate color palettes using artificial intelligence (OpenAI).
Home-page: https://github.com/psyonara/pailettes
Author: Helmut Irle
Author-email: me@helmut.dev
Requires-Python: >=3.10,<4.0
Classifier: Programming Language :: Python :: 3
Classifier: Programming Language :: Python :: 3.10
Classifier: Programming Language :: Python :: 3.11
Requires-Dist: openai (>=1.14.3,<2.0.0)
Requires-Dist: rich (>=13.7.1,<14.0.0)
Requires-Dist: typer[all] (>=0.11.0,<0.12.0)
